robbiejr_sc/__init__.py
robbiejr_sc/__main__.py
robbiejr_sc/install.sh
robbiejr_sc/robbiejr.sh
robbiejr_sc-1.0.0.dist-info/METADATA
robbiejr_sc-1.0.0.dist-info/WHEEL
robbiejr_sc-1.0.0.dist-info/entry_points.txt
robbiejr_sc-1.0.0.dist-info/top_level.txt
robbiejr_sc-1.0.0.dist-info/RECORD
