Metadata-Version: 2.4
Name: robbiejr-sc
Version: 1.0.0
Summary: A terminal command tool that installs and runs RobbieJr CDN Host Checker.
Author-email: Robbie Jr <robbiejr@example.com>
Classifier: Programming Language :: Python :: 3
Classifier: License :: OSI Approved :: MIT License
Classifier: Operating System :: POSIX :: Linux
Requires-Python: >=3.8
Requires-Dist: importlib-resources; python_version < "3.9"
